cognite/powerops/__init__.py
cognite/powerops/_version.py
cognite/powerops/cli.py
cognite/powerops/client/__init__.py
cognite/powerops/client/_generated/__init__.py
cognite/powerops/client/_generated/_api/__init__.py
cognite/powerops/client/_generated/_api/_core.py
cognite/powerops/client/_generated/_api/alert.py
cognite/powerops/client/_generated/_api/benchmarking_calculation_input.py
cognite/powerops/client/_generated/_api/benchmarking_calculation_input_shop_results.py
cognite/powerops/client/_generated/_api/benchmarking_calculation_output.py
cognite/powerops/client/_generated/_api/benchmarking_calculation_output_alerts.py
cognite/powerops/client/_generated/_api/benchmarking_calculation_output_benchmarking_results.py
cognite/powerops/client/_generated/_api/benchmarking_configuration_day_ahead.py
cognite/powerops/client/_generated/_api/benchmarking_configuration_day_ahead_assets_per_shop_model.py
cognite/powerops/client/_generated/_api/benchmarking_configuration_day_ahead_bid_configurations.py
cognite/powerops/client/_generated/_api/benchmarking_production_obligation_day_ahead.py
cognite/powerops/client/_generated/_api/benchmarking_result_day_ahead.py
cognite/powerops/client/_generated/_api/benchmarking_result_day_ahead_alerts.py
cognite/powerops/client/_generated/_api/benchmarking_shop_case.py
cognite/powerops/client/_generated/_api/benchmarking_shop_case_shop_files.py
cognite/powerops/client/_generated/_api/benchmarking_task_dispatcher_input_day_ahead.py
cognite/powerops/client/_generated/_api/benchmarking_task_dispatcher_output_day_ahead.py
cognite/powerops/client/_generated/_api/benchmarking_task_dispatcher_output_day_ahead_alerts.py
cognite/powerops/client/_generated/_api/benchmarking_task_dispatcher_output_day_ahead_benchmarking_sub_tasks.py
cognite/powerops/client/_generated/_api/bid_configuration_day_ahead.py
cognite/powerops/client/_generated/_api/bid_configuration_day_ahead_partials.py
cognite/powerops/client/_generated/_api/bid_document.py
cognite_power_ops-1.1.0.dist-info/LICENSE
cognite_power_ops-1.1.0.dist-info/METADATA
cognite_power_ops-1.1.0.dist-info/WHEEL
cognite_power_ops-1.1.0.dist-info/entry_points.txt
cognite_power_ops-1.1.0.dist-info/RECORD
