Metadata-Version: 2.3
Name: cognite-power-ops
Version: 1.1.0
Summary: SDK for power markets operations on Cognite Data Fusion
License: Apache 2.0
Author: Cognite
Author-email: support@cognite.com
Requires-Python: >=3.10,<3.13
Classifier: License :: Other/Proprietary License
Classifier: Programming Language :: Python :: 3
Classifier: Programming Language :: Python :: 3.10
Classifier: Programming Language :: Python :: 3.11
Classifier: Programming Language :: Python :: 3.12
Requires-Dist: PyYAML (>=6.0,<7.0)
Requires-Dist: StrEnum (>=0.4.15,<0.5.0) ; python_version < "3.11"
Requires-Dist: arrow (>=1.2.0,<2.0.0)
Requires-Dist: cachelib (>=0.13.0,<0.14.0)
Requires-Dist: cognite-pygen (>=1.2.21,<2.0.0)
Requires-Dist: cognite-sdk[pandas] (>=7.67.1)
Requires-Dist: dacite (>=1.8.1,<2.0.0)
Requires-Dist: deepdiff (>=6.3.0,<7.0.0)
Requires-Dist: loguru (>=0.7.0,<0.8.0)
Requires-Dist: pydantic (>=2.0,<3.0)
Requires-Dist: pydantic-settings (>=2.0,<3.0)
Requires-Dist: tabulate (>=0.9,<0.10)
Requires-Dist: toml (>=0.10)
Requires-Dist: tomli (>=2.0.1,<3.0.0) ; python_version < "3.11"
Requires-Dist: tomli-w (>=1.0.0,<2.0.0)
Requires-Dist: typer (>=0.12.0,<0.13.0)
Requires-Dist: typing_extensions (>=4)
